stacterm/__init__.py
stacterm/calendar.py
stacterm/cli.py
stacterm/utils.py
stacterm-0.1.0.dist-info/METADATA
stacterm-0.1.0.dist-info/WHEEL
stacterm-0.1.0.dist-info/entry_points.txt
stacterm-0.1.0.dist-info/top_level.txt
stacterm-0.1.0.dist-info/RECORD
