Metadata-Version: 2.1
Name: stacterm
Version: 0.1.0
Summary: STAC Items in the terminal
Home-page: https://github.com/stac-utils/stac-terminal
Author: Matthew Hanson
Author-email: matt.a.hanson@gmail.com
License: UNKNOWN
Keywords: An Awesome python module
Platform: UNKNOWN
Classifier: Intended Audience :: Information Technology
Classifier: Intended Audience :: Science/Research
Classifier: License :: OSI Approved :: MIT License
Classifier: Programming Language :: Python :: 3.6
Classifier: Programming Language :: Python :: 3.7
Classifier: Programming Language :: Python :: 3.8
Requires-Python: >=3
Requires-Dist: pandas (~=1.2.0)
Requires-Dist: termtables (~=0.2.3)
Requires-Dist: plotext (~=2.3.1)
Provides-Extra: dev
Requires-Dist: pytest ; extra == 'dev'
Requires-Dist: pytest-cov ; extra == 'dev'
Requires-Dist: pre-commit ; extra == 'dev'
Provides-Extra: test
Requires-Dist: pytest ; extra == 'test'
Requires-Dist: pytest-cov ; extra == 'test'
